odoo/addons/website_sale_product_pack/README.rst
odoo/addons/website_sale_product_pack/__init__.py
odoo/addons/website_sale_product_pack/__manifest__.py
odoo/addons/website_sale_product_pack/controllers/__init__.py
odoo/addons/website_sale_product_pack/controllers/main.py
odoo/addons/website_sale_product_pack/controllers/variant.py
odoo/addons/website_sale_product_pack/i18n/it.po
odoo/addons/website_sale_product_pack/i18n/website_sale_product_pack.pot
odoo/addons/website_sale_product_pack/models/__init__.py
odoo/addons/website_sale_product_pack/models/product_product.py
odoo/addons/website_sale_product_pack/models/product_template.py
odoo/addons/website_sale_product_pack/models/sale_order.py
odoo/addons/website_sale_product_pack/models/website.py
odoo/addons/website_sale_product_pack/readme/CONTRIBUTORS.md
odoo/addons/website_sale_product_pack/readme/DESCRIPTION.md
odoo/addons/website_sale_product_pack/readme/ROADMAP.md
odoo/addons/website_sale_product_pack/readme/USAGE.md
odoo/addons/website_sale_product_pack/static/description/icon.png
odoo/addons/website_sale_product_pack/static/description/index.html
odoo/addons/website_sale_product_pack/static/tests/tours/website_sale_product_pack_tour.js
odoo/addons/website_sale_product_pack/tests/__init__.py
odoo/addons/website_sale_product_pack/tests/test_website_sale_product_pack.py
odoo/addons/website_sale_product_pack/views/templates.xml
odoo_addon_website_sale_product_pack-17.0.2.0.1.dist-info/METADATA
odoo_addon_website_sale_product_pack-17.0.2.0.1.dist-info/WHEEL
odoo_addon_website_sale_product_pack-17.0.2.0.1.dist-info/top_level.txt
odoo_addon_website_sale_product_pack-17.0.2.0.1.dist-info/RECORD
