Metadata-Version: 2.1
Name: odoo-addon-website_sale_product_pack
Version: 17.0.2.0.1
Requires-Python: >=3.10
Requires-Dist: odoo-addon-sale_product_pack>=17.0dev,<17.1dev
Requires-Dist: odoo>=17.0a,<17.1dev
Summary: Compatibility module of product pack with e-commerce
Home-page: https://github.com/OCA/product-pack
License: AGPL-3
Author: Tecnativa, Odoo Community Association (OCA)
Author-email: support@odoo-community.org
Classifier: Programming Language :: Python
Classifier: Framework :: Odoo
Classifier: Framework :: Odoo :: 17.0
Classifier: License :: OSI Approved :: GNU Affero General Public License v3
